code/ex1/alu.v
// ΚΑΡΑΤΗΣ ΔΗΜΗΤΡΙΟΣ 10775
// 1. ALU MODULE

module alu
    #(parameter op_width = 32,
      parameter alu_op_width = 4)
    (
        input [op_width-1:0] op1, 
        input [op_width-1:0] op2,
        input [alu_op_width-1:0] alu_op,
        output zero,
        output reg [op_width-1:0] result,
        output reg ovf
    );

    // Ορισμός παραμέτρων βάσει του πίνακα alu_op 
    parameter [3:0] ALUOP_AND  = 4'b1000;
    parameter [3:0] ALUOP_OR   = 4'b1001;
    parameter [3:0] ALUOP_NOR  = 4'b1010;
    parameter [3:0] ALUOP_NAND = 4'b1011;
    parameter [3:0] ALUOP_XOR  = 4'b1100;
    parameter [3:0] ALUOP_ADD  = 4'b0100;
    parameter [3:0] ALUOP_SUB  = 4'b0101;
    parameter [3:0] ALUOP_MUL  = 4'b0110;
    parameter [3:0] ALUOP_SRL  = 4'b0000;
    parameter [3:0] ALUOP_SLL  = 4'b0001;
    parameter [3:0] ALUOP_SRA  = 4'b0010;
    parameter [3:0] ALUOP_SLA  = 4'b0011;

    always @(*) begin
        // Αρχικοποίηση εξόδων
        result = {op_width{1'b0}};
        ovf = 1'b0;

        case (alu_op)
            // Λογικές πύλες bit-προς-bit
            ALUOP_AND:  result = op1 & op2;
            ALUOP_OR:   result = op1 | op2;
            ALUOP_NOR:  result = ~(op1 | op2);
            ALUOP_NAND: result = ~(op1 & op2);
            ALUOP_XOR:  result = op1 ^ op2;

            // Πρόσθεση με έλεγχο υπερχείλισης προσήμου
            ALUOP_ADD: begin
                result = $signed(op1) + $signed(op2);
                ovf = (op1[31] == op2[31]) && (result[31] != op1[31]);
            end
            
            // Αφαίρεση με έλεγχο υπερχείλισης προσήμου
            ALUOP_SUB: begin
                result = $signed(op1) - $signed(op2);
                ovf = (op1[31] != op2[31]) && (result[31] != op1[31]);
            end

            // Πολλαπλασιασμός και έλεγχος αν χωράει στα 32-bit
            ALUOP_MUL: begin
                result = $signed(op1) * $signed(op2);
                if ($signed(op1) != 0 && ($signed(result) / $signed(op1) != $signed(op2)))
                    ovf = 1'b1;
                else
                    ovf = 1'b0;
            end

            // Πράξεις ολίσθησης
            ALUOP_SRL: result = op1 >> op2[4:0];
            ALUOP_SLL: result = op1 << op2[4:0];
            ALUOP_SRA: result = $signed(op1) >>> op2[4:0];
            ALUOP_SLA: result = $signed(op1) <<< op2[4:0];

            default: begin
                result = {op_width{1'b0}};
                ovf = 1'b0;
            end
        endcase
    end

    // Σήμα εξόδου αν το αποτέλεσμα είναι μηδέν
    assign zero = (result == {op_width{1'b0}});

endmodule

code/ex2/calc_enc.v
// ΚΑΡΑΤΗΣ ΔΗΜΗΤΡΙΟΣ 10775
// 2. CALCULATOR_ENCODER (CALC_ENC) MODULE

module calc_enc (
    input btnl,
    input btnr,
    input btnd,
    output [3:0] alu_op
);
    // Ενδιάμεσα σήματα (wires) για τις συνδέσεις των πυλών
    wire not_btnl, not_btnr, not_btnd;
    wire and0_top, and0_mid, and0_bot;
    wire or1_mid;
    wire and2_top, xor2_mid, not_xor2, and2_bot;
    wire and3_top, and3_bot;

    // Πύλες NOT για την αντιστροφή των εισόδων 
    not (not_btnl, btnl);
    not (not_btnr, btnr);
    not (not_btnd, btnd);

    // --- alu_op[0] (Σχήμα 2) ---
    and (and0_top, not_btnl, btnd);
    and (and0_mid, btnl, btnr);     
    and (and0_bot, and0_mid, not_btnd);
    or  (alu_op[0], and0_top, and0_bot);

    // --- alu_op[1] (Σχήμα 3) ---
    or  (or1_mid, not_btnr, not_btnd);
    and (alu_op[1], btnl, or1_mid);

    // --- alu_op[2] (Σχήμα 4) ---
    and (and2_top, not_btnl, btnr);
    xor (xor2_mid, btnr, btnd);
    not (not_xor2, xor2_mid);
    and (and2_bot, btnl, not_xor2);
    or  (alu_op[2], and2_top, and2_bot);

    // --- alu_op[3] (Σχήμα 5) ---
    and (and3_top, btnl, btnr);
    and (and3_bot, btnl, btnd);
    or  (alu_op[3], and3_top, and3_bot);

endmodule

code/ex2/calc.v
// ΚΑΡΑΤΗΣ ΔΗΜΗΤΡΙΟΣ 10775
// 2. CALCULATOR MODULE

`include "../ex1/alu.v"
`include "calc_enc.v"

module calc (
    input clk,
    input btnc,     
    input btnac,   
    input btnl,
    input btnr,
    input btnd,
    input [15:0] sw,    
    output [15:0] led   
);

    reg [15:0] accumulator; 
    wire [31:0] op1, op2, alu_result;
    wire [3:0] alu_op;
    wire alu_zero, alu_ovf;

    // Sign extension 16-bit -> 32-bit με χρήση concatenation 
    assign op1 = {{16{accumulator[15]}}, accumulator}; 
    assign op2 = {{16{sw[15]}}, sw};                   

    // Σύνδεση Κωδικοποιητή
    calc_enc encoder_inst (
        .btnl(btnl),
        .btnr(btnr),
        .btnd(btnd),
        .alu_op(alu_op)
    );

    // Σύνδεση ALU 
    alu alu_inst (
        .op1(op1),
        .op2(op2),
        .alu_op(alu_op),
        .zero(alu_zero),
        .result(alu_result),
        .ovf(alu_ovf)
    );

    // Σύγχρονη λογική Συσσωρευτή 
    always @(posedge clk) begin
        if (btnac) begin
            accumulator <= 16'h0000; // Σύγχρονος μηδενισμός 
        end else if (btnc) begin
            accumulator <= alu_result[15:0]; // Ενημέρωση με τα 16 LSB 
        end
    end

    // Σύνδεση accumulator με LEDs 
    assign led = accumulator;

endmodule

code/ex2/calc_tb.v
// ΚΑΡΑΤΗΣ ΔΗΜΗΤΡΙΟΣ 10775
// 2. CALCULATOR TESTBENCH


`timescale 1ns/1ps

module calc_tb;
    reg clk, btnc, btnac, btnl, btnr, btnd;
    reg [15:0] sw;
    wire [15:0] led;

    calc dut (
        .clk(clk), .btnc(btnc), .btnac(btnac), 
        .btnl(btnl), .btnr(btnr), .btnd(btnd), 
        .sw(sw), .led(led)
    );

    always #5 clk = ~clk;

    initial begin
        $dumpfile("calc_simulation.vcd");
        $dumpvars(0, calc_tb);
        clk = 0; btnc = 0; btnac = 0; btnl = 0; btnr = 0; btnd = 0; sw = 0;

        // 1. Reset (btnac) 
        #10 btnac = 1; #10 btnac = 0; #10;
        $display("1. Reset: LED=%h (Expected: 0000)", led);

        // 2. ADD: Acc(0) + sw(285a) = 285a 
        #10 sw = 16'h285a; btnl = 0; btnr = 1; btnd = 0;
        #10 btnc = 1; #10 btnc = 0; #10;
        $display("2. ADD: LED=%h (Expected: 285a)", led);

        // 3. XOR: Acc(285a) XOR sw(04c8) = 2c92 
        #10 sw = 16'h04c8; btnl = 1; btnr = 1; btnd = 1;
        #10 btnc = 1; #10 btnc = 0; #10;
        $display("3. XOR: LED=%h (Expected: 2c92)", led);

        // 4. SRL: Acc(2c92) >> sw(0005) = 0164 
        #10 sw = 16'h0005; btnl = 0; btnr = 0; btnd = 0;
        #10 btnc = 1; #10 btnc = 0; #10;
        $display("4. SRL: LED=%h (Expected: 0164)", led);

        // 5. NOR: Acc(0164) NOR sw(a085) = 5e1a 
        #10 sw = 16'ha085; btnl = 1; btnr = 0; btnd = 1;
        #10 btnc = 1; #10 btnc = 0; #10;
        $display("5. NOR: LED=%h (Expected: 5e1a)", led);

        // 6. MULT: Acc(5e1a) * sw(07fe) = 13cc 
        #10 sw = 16'h07fe; btnl = 1; btnr = 0; btnd = 0;
        #10 btnc = 1; #10 btnc = 0; #10;
        $display("6. MUL: LED=%h (Expected: 13cc)", led);

        // 7. SLL: Acc(13cc) << sw(0004) = 3cc0 
        #10 sw = 16'h0004; btnl = 0; btnr = 0; btnd = 1;
        #10 btnc = 1; #10 btnc = 0; #10;
        $display("7. SLL: LED=%h (Expected: 3cc0)", led);

        // 8. NAND: Acc(3cc0) NAND sw(fa65) = c7bf 
        #10 sw = 16'hfa65; btnl = 1; btnr = 1; btnd = 0;
        #10 btnc = 1; #10 btnc = 0; #10;
        $display("8. NAND: LED=%h (Expected: c7bf)", led);

        // 9. SUB: Acc(c7bf) - sw(b2e4) = 14db 
        #10 sw = 16'hb2e4; btnl = 0; btnr = 1; btnd = 1;
        #10 btnc = 1; #10 btnc = 0; #10;
        $display("9. SUB: LED=%h (Expected: 14db)", led);

        #50 $finish;
    end
endmodule

code/ex2/calc_simulation.vcd
$date
	Sat Jan 17 20:07:10 2026
$end
$version
	Icarus Verilog
$end
$timescale
	1ps
$end
$scope module calc_tb $end
$var wire 16 ! led [15:0] $end
$var reg 1 " btnac $end
$var reg 1 # btnc $end
$var reg 1 $ btnd $end
$var reg 1 % btnl $end
$var reg 1 & btnr $end
$var reg 1 ' clk $end
$var reg 16 ( sw [15:0] $end
$scope module dut $end
$var wire 1 " btnac $end
$var wire 1 # btnc $end
$var wire 1 $ btnd $end
$var wire 1 % btnl $end
$var wire 1 & btnr $end
$var wire 1 ' clk $end
$var wire 16 ) led [15:0] $end
$var wire 16 * sw [15:0] $end
$var wire 32 + op2 [31:0] $end
$var wire 32 , op1 [31:0] $end
$var wire 1 - alu_zero $end
$var wire 32 . alu_result [31:0] $end
$var wire 1 / alu_ovf $end
$var wire 4 0 alu_op [3:0] $end
$var reg 16 1 accumulator [15:0] $end
$scope module alu_inst $end
$var wire 32 2 op1 [31:0] $end
$var wire 32 3 op2 [31:0] $end
$var wire 1 - zero $end
$var wire 4 4 alu_op [3:0] $end
$var reg 1 / ovf $end
$var reg 32 5 result [31:0] $end
$upscope $end
$scope module encoder_inst $end
$var wire 1 6 and0_bot $end
$var wire 1 7 and0_mid $end
$var wire 1 8 and0_top $end
$var wire 1 9 and2_bot $end
$var wire 1 : and2_top $end
$var wire 1 ; and3_bot $end
$var wire 1 < and3_top $end
$var wire 1 $ btnd $end
$var wire 1 % btnl $end
$var wire 1 & btnr $end
$var wire 1 = not_btnd $end
$var wire 1 > not_btnl $end
$var wire 1 ? not_btnr $end
$var wire 1 @ not_xor2 $end
$var wire 1 A or1_mid $end
$var wire 1 B xor2_mid $end
$var wire 4 C alu_op [3:0] $end
$upscope $end
$upscope $end
$upscope $end
$enddefinitions $end
#0
$dumpvars
b0 C
0B
1A
1@
1?
1>
1=
0<
0;
0:
09
08
07
06
bx 5
b0 4
b0 3
bx 2
bx 1
b0 0
0/
bx .
x-
bx ,
b0 +
b0 *
bx )
b0 (
0'
0&
0%
0$
0#
0"
bx !
$end
#5000
1'
#10000
0'
1"
#15000
1-
b0 .
b0 5
b0 ,
b0 2
b0 !
b0 )
b0 1
1'
#20000
0'
0"
#25000
1'
#30000
0'
#35000
1'
#40000
0-
b10100001011010 .
b10100001011010 5
b100 0
b100 4
b100 C
0@
0?
1:
1B
0'
1&
b10100001011010 +
b10100001011010 3
b10100001011010 (
b10100001011010 *
#45000
1'
#50000
0'
1#
#55000
0-
b101000010110100 .
b101000010110100 5
b10100001011010 ,
b10100001011010 2
b10100001011010 !
b10100001011010 )
b10100001011010 1
1'
#60000
0'
0#
#65000
1'
#70000
0'
#75000
1'
#80000
19
0A
1@
0:
0=
0B
0>
17
b1100 0
b1100 4
b1100 C
1<
1;
0-
b10110010010010 .
b10110010010010 5
0'
1$
1%
b10011001000 +
b10011001000 3
b10011001000 (
b10011001000 *
#85000
1'
#90000
0'
1#
#95000
0-
b10100001011010 .
b10100001011010 5
b10110010010010 ,
b10110010010010 2
b10110010010010 !
b10110010010010 )
b10110010010010 1
1'
#100000
0'
0#
#105000
1'
#110000
0'
#115000
1'
#120000
1A
b0 0
b0 4
b0 C
1=
1?
1>
07
09
0<
0;
0-
b101100100 .
b101100100 5
0'
0$
0&
0%
b101 +
b101 3
b101 (
b101 *
#125000
1'
#130000
0'
1#
#135000
0-
b1011 .
b1011 5
b101100100 ,
b101100100 2
b101100100 !
b101100100 )
b101100100 1
1'
#140000
0'
0#
#145000
1'
#150000
0'
#155000
1'
#160000
0@
0=
1B
0>
b1010 0
b1010 4
b1010 C
09
1;
0-
b101111000011010 .
b101111000011010 5
0'
1$
1%
b11111111111111111010000010000101 +
b11111111111111111010000010000101 3
b1010000010000101 (
b1010000010000101 *
#165000
1'
#170000
0'
1#
#175000
0-
b101100000 .
b101100000 5
b101111000011010 ,
b101111000011010 2
b101111000011010 !
b101111000011010 )
b101111000011010 1
1'
#180000
0'
0#
#185000
1'
#190000
0'
#195000
1'
#200000
19
1@
b110 0
b110 4
b110 C
1=
0B
0;
0-
b10111100000001001111001100 .
b10111100000001001111001100 5
0'
0$
b11111111110 +
b11111111110 3
b11111111110 (
b11111111110 *
#205000
1'
#210000
0'
1#
#215000
0-
b100111100011100001101000 .
b100111100011100001101000 5
b1001111001100 ,
b1001111001100 2
b1001111001100 !
b1001111001100 )
b1001111001100 1
1'
#220000
0'
0#
#225000
1'
#230000
0'
#235000
1'
#240000
0@
0=
18
1B
1>
b1 0
b1 4
b1 C
09
0-
b10011110011000000 .
b10011110011000000 5
0'
1$
0%
b100 +
b100 3
b100 (
b100 *
#245000
1'
#250000
0'
1#
#255000
0-
b111100110000000000 .
b111100110000000000 5
b11110011000000 ,
b11110011000000 2
b11110011000000 !
b11110011000000 )
b11110011000000 1
1'
#260000
0'
0#
#265000
1'
#270000
0'
#275000
1'
#280000
16
1=
08
0?
0>
17
b1011 0
b1011 4
b1011 C
1<
0-
b11111111111111111100011110111111 .
b11111111111111111100011110111111 5
0'
0$
1&
1%
b11111111111111111111101001100101 +
b11111111111111111111101001100101 3
b1111101001100101 (
b1111101001100101 *
#285000
1'
#290000
0'
1#
#295000
0-
b11110111011010 .
b11110111011010 5
b11111111111111111100011110111111 ,
b11111111111111111100011110111111 2
b1100011110111111 !
b1100011110111111 )
b1100011110111111 1
1'
#300000
0'
0#
#305000
1'
#310000
0'
#315000
1'
#320000
0A
1@
1:
06
0=
18
0B
1>
07
b101 0
b101 4
b101 C
0<
0-
b1010011011011 .
b1010011011011 5
0'
1$
0%
b11111111111111111011001011100100 +
b11111111111111111011001011100100 3
b1011001011100100 (
b1011001011100100 *
#325000
1'
#330000
0'
1#
#335000
0-
b110000111110111 .
b110000111110111 5
b1010011011011 ,
b1010011011011 2
b1010011011011 !
b1010011011011 )
b1010011011011 1
1'
#340000
0'
0#
